datreant.core-0.7.1-py2.7-nspkg.pth
datreant/core/collections.py
datreant/core/__init__.py
datreant/core/treants.py
datreant/core/limbs.py
datreant/core/attach.py
datreant/core/agglimbs.py
datreant/core/util.py
datreant/core/manipulators.py
datreant/core/trees.py
datreant/core/rsync.py
datreant/core/filesystem.py
datreant/core/tests/__init__.py
datreant/core/tests/test_treants.py
datreant/core/tests/test_rsync.py
datreant/core/tests/test_manipulators.py
datreant/core/tests/test_collections.py
datreant/core/tests/test_locks.py
datreant/core/tests/test_trees.py
datreant/core/tests/test_filesystem.py
datreant/core/backends/__init__.py
datreant/core/backends/core.py
datreant/core/backends/statefiles.py
datreant.core-0.7.1.dist-info/metadata.json
datreant.core-0.7.1.dist-info/top_level.txt
datreant.core-0.7.1.dist-info/DESCRIPTION.rst
datreant.core-0.7.1.dist-info/namespace_packages.txt
datreant.core-0.7.1.dist-info/METADATA
datreant.core-0.7.1.dist-info/WHEEL
datreant.core-0.7.1.dist-info/RECORD
