Metadata-Version: 2.0
Name: datreant.core
Version: 0.7.1
Summary: persistent, pythonic trees for heterogeneous data
Home-page: http://datreant.org/
Author: David Dotson
Author-email: dotsdl@gmail.com
License: BSD
Platform: UNKNOWN
Classifier: Development Status :: 4 - Beta
Classifier: Environment :: Console
Classifier: Intended Audience :: Science/Research
Classifier: License :: OSI Approved :: BSD License
Classifier: Operating System :: POSIX
Classifier: Programming Language :: Python
Classifier: Topic :: Scientific/Engineering
Classifier: Topic :: Software Development :: Libraries :: Python Modules
Requires-Dist: asciitree
Requires-Dist: pathlib2
Requires-Dist: scandir
Requires-Dist: six
Requires-Dist: fuzzywuzzy
